pymajic/__init__.py
pymajic/store.py
pymajic-1.0.dist-info/METADATA
pymajic-1.0.dist-info/WHEEL
pymajic-1.0.dist-info/entry_points.txt
pymajic-1.0.dist-info/top_level.txt
pymajic-1.0.dist-info/RECORD
