Metadata-Version: 2.1
Name: pymajic
Version: 1.0
Summary: PyMajic is a Python package that simplifies working with Django projects by providing convenient commands for environment management, custom commands, and more.
Home-page: https://github.com/Codewithshagbaor/PyMajic
Author: Shagbaor Agber
Author-email: dxtlive@gmail.com
Keywords: Django,project management,virtual environment,Django development,utility,command-line tool,workflow optimization,automation
Requires-Dist: Django
Requires-Dist: requests
